{
  "id": 179,
  "name": "mareep",
  "generation": "2",
  "types": [
    "electric"
  ],
  "base_stats": {
    "hp": 55,
    "attack": 40,
    "defense": 40,
    "sp_atk": 65,
    "sp_def": 45,
    "speed": 35
  },
  "base_experience": 56,
  "growth_rate": "medium-slow",
  "capture_rate": 235,
  "gender_rate": 4,
  "hatch_cycles": 20,
  "base_friendship": 70,
  "egg_groups": [
    "monster",
    "ground"
  ],
  "abilities": {
    "primary": "static",
    "secondary": null,
    "hidden": "plus"
  },
  "moves": {
    "level_up": [
      {
        "level": 1,
        "name": "growl"
      },
      {
        "level": 1,
        "name": "tackle"
      },
      {
        "level": 4,
        "name": "thunder-wave"
      },
      {
        "level": 8,
        "name": "thunder-shock"
      },
      {
        "level": 11,
        "name": "cotton-spore"
      },
      {
        "level": 15,
        "name": "charge"
      },
      {
        "level": 18,
        "name": "take-down"
      },
      {
        "level": 25,
        "name": "confuse-ray"
      },
      {
        "level": 29,
        "name": "power-gem"
      },
      {
        "level": 30,
        "name": "light-screen"
      },
      {
        "level": 32,
        "name": "discharge"
      },
      {
        "level": 37,
        "name": "thunder"
      },
      {
        "level": 39,
        "name": "signal-beam"
      }
    ],
    "machines": [
      "attract",
      "charge-beam",
      "double-team",
      "facade",
      "flash",
      "frustration",
      "hidden-power",
      "iron-tail",
      "light-screen",
      "protect",
      "rain-dance",
      "rest",
      "return",
      "safeguard",
      "secret-power",
      "shock-wave",
      "substitute",
      "swagger",
      "thunder",
      "thunder-wave",
      "thunderbolt",
      "toxic"
    ]
  },
  "evolution": {
    "previous": null,
    "next": [
      180
    ],
    "root": 179,
    "next_details": []
  }
}