{
  "id": "twinleaf_town_home_interior",
  "name": "Downstairs",
  "actions": [
    {
      "label": "Talk to Mom",
      "type": "dialogue",
      "dialogue_key": "intro.rival.intro",
      "fallback_text": "MOM: Have a nice day dear!",
      "set_flag": "rival_introduced"
    },
    { "label": "Exit to Twinleaf Town", "type": "move", "target": "twinleaf_town_outside", "set_flag": "left_home" },
    { "label": "Go upstairs", "type": "move", "target": "twinleaf_town_bedroom" },
    { "label": "Return to Main Menu", "type": "exit" }
  ],
  "children": ["twinleaf_town_outside"]
}
